{
  "id": 24426,
  "slug": "ondas-do-leste-barra-da-lagoa-florianopolis-sc",
  "title": "Ondas do Leste, Barra da Lagoa",
  "category": "lancamento",
  "price": {
    "prefix": "A partir de",
    "display": "R$240,000",
    "amount": 240000,
    "currency": "BRL"
  },
  "address": {
    "street": "Av. Cidade de Córdoba, Barra da Lagoa, Florianópolis SC",
    "country": "",
    "state": {
      "slug": "sc",
      "name": "Santa Catarina"
    },
    "city": {
      "slug": "florianopolis",
      "name": "Florianópolis"
    },
    "neighborhood": {
      "slug": "barra-da-lagoa",
      "name": "Barra da Lagoa"
    }
  },
  "overview": {
    "code": "1669",
    "bedrooms": 1,
    "bathrooms": 1,
    "garages": null,
    "sizeSqm": 20.482,
    "deliveryYear": "Jun/30"
  },
  "types": [
    {
      "slug": "apartment",
      "name": "Lançamentos"
    }
  ],
  "statuses": [
    {
      "slug": "jul-30",
      "name": "Jul/30"
    }
  ],
  "labels": [
    {
      "slug": "1-e-2-dorms",
      "name": "1 e 2 dorms."
    }
  ],
  "featureSlugs": [],
  "features": [],
  "descriptionHtml": "<ul data-start=\"586\" data-end=\"835\">\n<li data-start=\"586\" data-end=\"622\"><strong data-start=\"625\" data-end=\"650\">Apartamentos 1 suíte:</strong> 40,96 m² + 1 vaga de garagem<strong data-start=\"662\" data-end=\"683\"> a partir de R$ 583.000,00</strong></li>\n<li data-start=\"686\" data-end=\"764\">\n<p data-start=\"688\" data-end=\"764\"><strong data-start=\"688\" data-end=\"729\">Apartamentos 2 dormitórios (1 suíte):</strong> 61,44 m² + 1 vaga de garagem<strong data-start=\"741\" data-end=\"762\"> a partir de R$ 788.000,00</strong></p>\n</li>\n<li data-start=\"686\" data-end=\"764\">\n<p data-start=\"688\" data-end=\"764\"><strong data-start=\"767\" data-end=\"782\">Coberturas:</strong> opções com <strong data-start=\"794\" data-end=\"810\">2 e 3 suítes</strong> + 2 vagas de garagem<strong data-start=\"813\" data-end=\"835\"> a partir de R$ 942.000,00</strong></p>\n</li>\n</ul>\n<p>Entrada parcelada em 9X + parcelas 44X + reforços 8X</p>\n<ul>\n<li><em>Valores e disponibilidade podem sofrer alteração sem aviso prévio.</em></li>\n<li><em>Condições de pagamento flexíveis.</em></li>\n<li><em>Valores atualizados em: 27/05/2026</em></li>\n</ul>\n<p><strong data-start=\"2\" data-end=\"20\">Ondas do Leste</strong> é um lançamento pensado para quem quer viver (ou investir) a poucos metros da praia, na <strong data-start=\"109\" data-end=\"143\">Barra da Lagoa – Florianópolis</strong>, unindo o clima leve do Leste da Ilha com uma arquitetura contemporânea e áreas comuns completas para o dia a dia e para a temporada.</p>\n<h5 data-start=\"317\" data-end=\"331\">Localização</h5>\n<p data-start=\"332\" data-end=\"513\">Implantado na <strong data-start=\"346\" data-end=\"371\">Av. Cidade de Córdoba</strong>, em ponto estratégico na Barra da Lagoa, com acesso rápido ao mar e aos principais atrativos da região.</p>\n<h5 data-start=\"515\" data-end=\"528\">Tipologias</h5>\n<p data-start=\"529\" data-end=\"584\">Plantas inteligentes, com proposta moderna e funcional:</p>\n<ul data-start=\"586\" data-end=\"835\">\n<li data-start=\"623\" data-end=\"685\">\n<p data-start=\"625\" data-end=\"685\"><strong data-start=\"625\" data-end=\"650\">Apartamentos 1 suíte:</strong> 40,96 m² + <strong data-start=\"662\" data-end=\"683\">1 vaga de garagem</strong></p>\n</li>\n<li data-start=\"686\" data-end=\"764\">\n<p data-start=\"688\" data-end=\"764\"><strong data-start=\"688\" data-end=\"729\">Apartamentos 2 dormitórios (1 suíte):</strong> 61,44 m² + <strong data-start=\"741\" data-end=\"762\">1 vaga de garagem</strong></p>\n</li>\n<li data-start=\"765\" data-end=\"835\">\n<p data-start=\"767\" data-end=\"835\"><strong data-start=\"767\" data-end=\"782\">Coberturas:</strong> opções com <strong data-start=\"794\" data-end=\"810\">2 e 3 suítes</strong> + <strong data-start=\"813\" data-end=\"835\">2 vagas de garagem</strong></p>\n</li>\n</ul>\n<h5 data-start=\"837\" data-end=\"880\">Mais de 1.000 m² de lazer e conveniência</h5>\n<p data-start=\"881\" data-end=\"1263\">Um projeto completo, com ambientes planejados para diferentes estilos de rotina: <strong data-start=\"962\" data-end=\"990\">coworking e meeting room</strong>, <strong data-start=\"992\" data-end=\"1017\">academia e espaço zen</strong>, <strong data-start=\"1019\" data-end=\"1038\">salão de festas</strong>, <strong data-start=\"1040\" data-end=\"1051\">rooftop</strong>, <strong data-start=\"1053\" data-end=\"1064\">piscina</strong>, <strong data-start=\"1066\" data-end=\"1078\">spot bar</strong>, <strong data-start=\"1080\" data-end=\"1093\">fireplace</strong>, <strong data-start=\"1095\" data-end=\"1109\">playground</strong>, <strong data-start=\"1111\" data-end=\"1133\">pet place/pet care</strong>, <strong data-start=\"1135\" data-end=\"1149\">lavanderia</strong>, além de <strong data-start=\"1159\" data-end=\"1175\">mini mercado</strong> e <strong data-start=\"1178\" data-end=\"1192\">pranchário</strong> (perfeito para a vibe da Barra).</p>\n<p data-start=\"881\" data-end=\"1263\">No térreo, o empreendimento ainda conta com <strong data-start=\"1309\" data-end=\"1329\">hall residencial</strong>, <strong data-start=\"1331\" data-end=\"1353\">2 lojas comerciais</strong>, <strong data-start=\"1355\" data-end=\"1373\">estacionamento</strong>, <strong data-start=\"1375\" data-end=\"1391\">bicicletário</strong> e área de apoio/serviços do condomínio.</p>\n<h5 data-start=\"1471\" data-end=\"1511\">Acabamentos e diferenciais (unidades)</h5>\n<ul data-start=\"1575\" data-end=\"1818\">\n<li data-start=\"1575\" data-end=\"1598\">\n<p data-start=\"1577\" data-end=\"1598\"><strong data-start=\"1577\" data-end=\"1598\">Fechadura digital</strong></p>\n</li>\n<li data-start=\"1599\" data-end=\"1640\">\n<p data-start=\"1601\" data-end=\"1640\"><strong data-start=\"1601\" data-end=\"1640\">Infraestrutura para ar-condicionado</strong></p>\n</li>\n<li data-start=\"1641\" data-end=\"1666\">\n<p data-start=\"1643\" data-end=\"1666\"><strong data-start=\"1643\" data-end=\"1666\">Piso em porcelanato</strong></p>\n</li>\n<li data-start=\"1667\" data-end=\"1697\">\n<p data-start=\"1669\" data-end=\"1697\"><strong data-start=\"1669\" data-end=\"1697\">Nicho no box do banheiro</strong></p>\n</li>\n<li data-start=\"1698\" data-end=\"1715\">\n<p data-start=\"1700\" data-end=\"1715\"><strong data-start=\"1700\" data-end=\"1715\">Ralo linear</strong></p>\n</li>\n<li data-start=\"1716\" data-end=\"1818\">\n<p data-start=\"1718\" data-end=\"1818\"><strong data-start=\"1718\" data-end=\"1780\">Tubulação de hidráulica envelopada para atenuação de ruído</strong></p>\n</li>\n</ul>\n<h5 data-start=\"1820\" data-end=\"1849\">Diferenciais do condomínio</h5>\n<p data-start=\"1850\" data-end=\"2078\">Soluções voltadas à eficiência e segurança, como <strong data-start=\"1899\" data-end=\"1934\">aproveitamento de água da chuva</strong>, <strong data-start=\"1936\" data-end=\"1965\">monitoramento por câmeras</strong>, <strong data-start=\"1967\" data-end=\"2006\">infraestrutura para portaria remota</strong> e <strong data-start=\"2009\" data-end=\"2039\">controle de acesso digital</strong>.</p>",
  "floorPlans": [],
  "images": [
    {
      "file": "images/01-Captura-de-tela-2026-03-04-174713.png",
      "role": "gallery"
    },
    {
      "file": "images/02-Captura-de-tela-2026-03-04-174734.png",
      "role": "gallery"
    },
    {
      "file": "images/03-Captura-de-tela-2026-03-04-174853.png",
      "role": "gallery"
    },
    {
      "file": "images/04-Captura-de-tela-2026-03-04-174755.png",
      "role": "gallery"
    },
    {
      "file": "images/05-Captura-de-tela-2026-03-04-174909.png",
      "role": "gallery"
    },
    {
      "file": "images/06-Captura-de-tela-2026-03-04-174933-1.png",
      "role": "gallery"
    },
    {
      "file": "images/07-Captura-de-tela-2026-03-04-174946.png",
      "role": "gallery"
    },
    {
      "file": "images/08-Captura-de-tela-2026-03-04-175001.png",
      "role": "gallery"
    },
    {
      "file": "images/09-Captura-de-tela-2026-03-04-175015.png",
      "role": "gallery"
    },
    {
      "file": "images/10-Captura-de-tela-2026-03-04-175029.png",
      "role": "gallery"
    },
    {
      "file": "images/11-Captura-de-tela-2026-03-04-175042.png",
      "role": "gallery"
    },
    {
      "file": "images/12-Captura-de-tela-2026-03-04-175054.png",
      "role": "gallery"
    },
    {
      "file": "images/13-Captura-de-tela-2026-03-04-175108.png",
      "role": "gallery"
    },
    {
      "file": "images/14-Captura-de-tela-2026-03-04-175122.png",
      "role": "gallery"
    },
    {
      "file": "images/15-Captura-de-tela-2026-03-04-175135.png",
      "role": "gallery"
    },
    {
      "file": "images/16-Captura-de-tela-2026-03-04-175201.png",
      "role": "gallery"
    }
  ],
  "videoUrl": "https://www.youtube.com/embed/XgTfaP86ph0?feature=oembed",
  "sourceUrl": "https://lancamentossc.com.br/site/property/ondas-do-leste-barra-da-lagoa-florianopolis-sc/",
  "importedAt": "2026-05-30T18:43:59.499Z",
  "kind": "apartamento"
}
